Metadata-Version: 1.0
Name: sumon
Version: 0.1
Summary: Gaussian distributions
Home-page: UNKNOWN
Author: Sumon Bhattacharya
Author-email: sumonbhattacharjee599@gmail.com
License: UNKNOWN
Platform: UNKNOWN
